{
  "openapi": "3.1.0",
  "info": {
    "version": "1.0.0",
    "title": "My Zuplo API"
  },
  "paths": {
    "/path-0": {
      "x-zuplo-path": {
        "pathMode": "open-api"
      },
      "get": {
        "summary": "New Route",
        "description": "Lorem ipsum dolor sit amet, **consectetur adipiscing** elit, sed do `eiusmod tempor` incididunt ut labore et dolore magna aliqua.",
        "x-zuplo-route": {
          "corsPolicy": "none",
          "handler": {
            "export": "urlForwardHandler",
            "module": "$import(@zuplo/runtime)",
            "options": {
              "baseUrl": "https://echo.zuplo.io"
            }
          },
          "policies": {
            "inbound": [
              "api-key-inbound",
              "monetization-inbound"
            ]
          }
        },
        "operationId": "8a06b2d8-ce06-4b81-8750-cb1e69256fd7"
      }
    }
  }
}